echotest/EchoTest.py
echotest/__init__.py
echotest/cli.py
echotest/controllers/baseline.py
echotest/controllers/main.py
echotest/controllers/test.py
echotest/factories/embeddings_factory.py
echotest/factories/llm_factory.py
echotest/schemas/baseline_schema.py
echotest/schemas/generate_baseline_schema.py
echotest/schemas/test_data_schema.py
echotest/services/embeddings/EmbeddingsService.py
echotest/services/embeddings/GeminiEmbeddings.py
echotest/services/embeddings/OpenAIEmbeddings.py
echotest/services/llms/AnthropicService.py
echotest/services/llms/GeminiService.py
echotest/services/llms/LLMService.py
echotest/services/llms/OpenAIService.py
echotest/utils/argument_utils.py
echotest/utils/file_utils.py
echotest/utils/vector_utils.py
echotest-0.15.0.dist-info/LICENSE
echotest-0.15.0.dist-info/METADATA
echotest-0.15.0.dist-info/WHEEL
echotest-0.15.0.dist-info/entry_points.txt
echotest-0.15.0.dist-info/RECORD
